secs/__init__.py
secs/app.py
secs/cost.py
secs/cube_state.py
secs/looped_phased_solver.py
secs/moves.py
secs/solver.py
secs/utils.py
secs/templates/index.html
secspp-0.1.2.dist-info/METADATA
secspp-0.1.2.dist-info/WHEEL
secspp-0.1.2.dist-info/entry_points.txt
secspp-0.1.2.dist-info/top_level.txt
secspp-0.1.2.dist-info/RECORD
