Metadata-Version: 2.4
Name: secspp
Version: 0.1.2
Summary: SECS++ Rubik's Cube Solver using phased and looped solving logic
Author-email: "P. Jeba Selvan Andrew" <your_email@example.com>
License: MIT
Requires-Python: >=3.9
Requires-Dist: flask
Requires-Dist: kociemba
Provides-Extra: dev
Requires-Dist: pytest; extra == "dev"
Requires-Dist: black; extra == "dev"
Requires-Dist: isort; extra == "dev"
